certbot_dns_aliyun_next/__init__.py
certbot_dns_aliyun_next/aliyun_client.py
certbot_dns_aliyun_next/dns_aliyun_next.py
certbot_dns_aliyun_next-1.0.7.dist-info/licenses/LICENSE
certbot_dns_aliyun_next-1.0.7.dist-info/METADATA
certbot_dns_aliyun_next-1.0.7.dist-info/WHEEL
certbot_dns_aliyun_next-1.0.7.dist-info/entry_points.txt
certbot_dns_aliyun_next-1.0.7.dist-info/top_level.txt
certbot_dns_aliyun_next-1.0.7.dist-info/RECORD
