Metadata-Version: 2.4
Name: certbot-dns-aliyun-next
Version: 1.0.7
Summary: 阿里云DNS插件，用于Certbot的DNS-01验证
Home-page: https://github.com/tiyee/certbot-dns-aliyun-next
Author: tiyee
Author-email: tiyee <tiyee@live.com>
License: MIT
Project-URL: Homepage, https://github.com/tiyee/certbot-dns-aliyun-next
Project-URL: Repository, https://github.com/tiyee/certbot-dns-aliyun-next
Project-URL: Issues, https://github.com/tiyee/certbot-dns-aliyun-next/issues
Project-URL: Documentation, https://github.com/tiyee/certbot-dns-aliyun-next/blob/master/README.md
Keywords: certbot-dns,certbot-plugin,certbot-dns-plugin,certbot-dns-authenticator,certbot-aliyun
Classifier: Development Status :: 4 - Beta
Classifier: Environment :: Plugins
Classifier: License :: OSI Approved :: MIT License
Classifier: Intended Audience :: System Administrators
Classifier: Operating System :: POSIX
Classifier: Operating System :: POSIX :: Linux
Classifier: Programming Language :: Python
Classifier: Programming Language :: Python :: 3
Classifier: Programming Language :: Python :: 3.8
Classifier: Programming Language :: Python :: 3.9
Classifier: Programming Language :: Python :: 3.10
Classifier: Programming Language :: Python :: 3.11
Classifier: Programming Language :: Python :: 3.12
Classifier: Programming Language :: Python :: 3.13
Classifier: Programming Language :: Python :: 3.14
Classifier: Topic :: Internet :: WWW/HTTP
Classifier: Topic :: Security
Classifier: Topic :: System :: Installation/Setup
Classifier: Topic :: System :: Networking
Classifier: Topic :: System :: Systems Administration
Classifier: Topic :: Utilities
Requires-Python: >=3.8
License-File: LICENSE
Requires-Dist: certbot>=3.0.0
Requires-Dist: zope
Requires-Dist: alibabacloud-alidns20150109>=3.0.0
Requires-Dist: alibabacloud-tea-openapi>=0.3.0
Requires-Dist: alibabacloud-tea-util>=0.3.0
Requires-Dist: alibabacloud-endpoint-util>=0.0.3
Requires-Dist: setuptools>=60.0.0
Dynamic: author
Dynamic: home-page
Dynamic: license-file
Dynamic: requires-python
